Metadata-Version: 1.0
Name: xz29-probability
Version: 0.1
Summary: Gaussian distributions
Home-page: UNKNOWN
Author: Kaitlyn Martinez
Author-email: martinez.kaitlyn55@gmail.com
License: UNKNOWN
Platform: UNKNOWN
